[
  {
    "name":"img/self-tag-2_359af50.png",
    "id":"全家出游",
    "price":9,
    "content":"<白鹿原影视城穿越硝烟·真人CS重现二虎守长安自驾1日游>",
    "main":"白鹿原影视城打开历史大门，带您感受战火纷飞与现代科技的激情碰撞",
    "aim":"白鹿原影视城",
    "img":"img/20160830103347714.jpg",
    "distance":12
    

  },
  {
    "name":"img/self-tag-1_617b72b.png",
    "id":"夜游法门",
    "price":518,
    "content":"夜游法门寺传灯祈福·住佛光阁酒店双人自驾自由行",
    "main":"一人价双人游，观赏夜晚不一样的法门寺，体验充满佛文化气息的晚间活动",
    "aim":"传灯祈福",
    "img":"img/20160825034900950.jpg",
    "distance":60

  },
  {
    "name":"img/self-tag-2_359af50.png",
    "id":"登山探险",
    "price":9,
    "content":"【在G318看一眼最后的风景】<川进青出高端自驾16日游>多团期",
    "main":"把我的心洗净 把我的魂唤醒 把我的梦实现 把我的情留住",
    "aim":"川藏南线",
    "img":"img/20160621052413878.jpg",
    "distance":110

  },
  {
    "name":"img/self-tag-1_617b72b.png",
    "id":"随时出发",
    "price":158,
    "content":"【秦岭里的香格里拉·关中后花园】<黄柏塬生态休闲自驾2日游>",
    "main":"一人价双人游，秦岭最具原始生态的地区之一，被誉为“秦岭里的香格里拉”",
    "aim":"游山玩水",
    "img":"img/20160620052605505.jpg",
    "distance":160

  },
  {
    "name":"img/self-tag-2_359af50.png",
    "id":"随时出发",
    "price":298,
    "content":"柞水景丽大酒店",
    "main":"牛背梁高端4星级度假酒店，体验高品质的氧吧酒店，和农家乐说拜拜",
    "aim":"休闲度假",
    "img":"img/20160812061126416.jpg",
    "distance":60

  },
  {
    "name":"img/self-tag-2_359af50.png",
    "id":"全家出游",
    "price":9,
    "content":"<白鹿原影视城穿越硝烟·真人CS重现二虎守长安自驾1日游>",
    "main":"白鹿原影视城打开历史大门，带您感受战火纷飞与现代科技的激情碰撞",
    "aim":"白鹿原影视城",
    "img":"img/20160830103347714.jpg",
    "distance":12

  },
  {
    "name":"img/self-tag-1_617b72b.png",
    "id":"夜游法门",
    "price":518,
    "content":"夜游法门寺传灯祈福·住佛光阁酒店双人自驾自由行",
    "main":"一人价双人游，观赏夜晚不一样的法门寺，体验充满佛文化气息的晚间活动",
    "aim":"传灯祈福",
    "img":"img/20160825034900950.jpg",
    "distance":130

  },
  {
    "name":"img/self-tag-2_359af50.png",
    "id":"登山探险",
    "price":9,
    "content":"【在G318看一眼最后的风景】<川进青出高端自驾16日游>多团期",
    "main":"把我的心洗净 把我的魂唤醒 把我的梦实现 把我的情留住",
    "aim":"川藏南线",
    "img":"img/20160621052413878.jpg",
    "distance":160

  },
  {
    "name":"img/self-tag-1_617b72b.png",
    "id":"随时出发",
    "price":158,
    "content":"【秦岭里的香格里拉·关中后花园】<黄柏塬生态休闲自驾2日游>",
    "main":"一人价双人游，秦岭最具原始生态的地区之一，被誉为“秦岭里的香格里拉”",
    "aim":"游山玩水",
    "img":"img/20160620052605505.jpg",
    "distance":90

  },
  {
    "name":"img/self-tag-2_359af50.png",
    "id":"随时出发",
    "price":298,
    "content":"柞水景丽大酒店",
    "main":"牛背梁高端4星级度假酒店，体验高品质的氧吧酒店，和农家乐说拜拜",
    "aim":"休闲度假",
    "img":"img/20160812061126416.jpg",
    "distance":100

  }
]